dpymenus/__init__.py
dpymenus/base_menu.py
dpymenus/button_menu.py
dpymenus/constants/__init__.py
dpymenus/exceptions.py
dpymenus/hooks.py
dpymenus/page.py
dpymenus/paginated_menu.py
dpymenus/poll.py
dpymenus/sessions/__init__.py
dpymenus/sessions/session.py
dpymenus/settings/__init__.py
dpymenus/template.py
dpymenus/text_menu.py
dpymenus/types/__init__.py
dpymenus-2.1.5.dist-info/entry_points.txt
dpymenus-2.1.5.dist-info/LICENSE.md
dpymenus-2.1.5.dist-info/WHEEL
dpymenus-2.1.5.dist-info/METADATA
dpymenus-2.1.5.dist-info/RECORD
