Metadata-Version: 2.1
Name: dpymenus
Version: 2.1.5
Summary: Simplified menus for discord.py developers.
Home-page: https://dpymenus.com
License: MIT
Keywords: discord.py,discord bot,menus,reaction buttons
Author: Rob Wagner
Author-email: rob@robwagner.dev
Requires-Python: >=3.8,<4.0
Classifier: Development Status :: 5 - Production/Stable
Classifier: Intended Audience :: Developers
Classifier: License :: OSI Approved :: MIT License
Classifier: Operating System :: OS Independent
Classifier: Programming Language :: Python :: 3
Classifier: Programming Language :: Python :: 3.8
Classifier: Programming Language :: Python :: 3.9
Classifier: Topic :: Communications :: Chat
Classifier: Typing :: Typed
Requires-Dist: discord.py (>=1.7,<2.0)
Requires-Dist: emoji (>=1.2,<2.0)
Requires-Dist: toml (>=0.10,<0.11)
Project-URL: Repository, https://github.com/robertwayne/dpymenus
